pdfbrain/__init__.py
pdfbrain/pdf_file.py
pdfbrain/pdf_page.py
pdfbrain/pdf_text_page.py
pdfbrain/tools.py
pdfbrain/test/__init__.py
pdfbrain/test/test_smoke.py
pdfbrain/test/test_text.py
pdfbrain-0.0.5.dist-info/LICENSE
pdfbrain-0.0.5.dist-info/METADATA
pdfbrain-0.0.5.dist-info/WHEEL
pdfbrain-0.0.5.dist-info/top_level.txt
pdfbrain-0.0.5.dist-info/RECORD
